mapi/__init__.py
mapi/__version__.py
mapi/compatibility.py
mapi/endpoints.py
mapi/exceptions.py
mapi/metadata.py
mapi/providers.py
mapi/utils.py
tests/__init__.py
tests/conftest.py
tests/test_utils.py
tests/endpoints/__init__.py
tests/endpoints/test_endpoints_omdb.py
tests/endpoints/test_endpoints_tmdb.py
tests/endpoints/test_endpoints_tvdb.py
tests/metadata/__init__.py
tests/metadata/test_metadata.py
tests/metadata/test_metadata_movie.py
tests/metadata/test_metadata_television.py
tests/providers/__init__.py
tests/providers/test_providers.py
tests/providers/test_providers_omdb.py
tests/providers/test_providers_tmdb.py
tests/providers/test_providers_tvdb.py
mapi-3.9.0.dist-info/METADATA
mapi-3.9.0.dist-info/WHEEL
mapi-3.9.0.dist-info/top_level.txt
mapi-3.9.0.dist-info/RECORD
