Metadata-Version: 2.1
Name: mapi
Version: 3.9.0
Summary: Python library which provides a high-level interface for media database providers, allowing users to search for television and movie metadata using a simple interface
Home-page: https://github.com/jkwill87/mapi
Author: Jessy Williams
Author-email: jessy@jessywilliams.com
License: MIT
Platform: UNKNOWN
Requires-Dist: appdirs (==1.*)
Requires-Dist: requests (==2.*)
Requires-Dist: requests-cache (>=0.4)
